[
  {
    "test_type": "Функціональний",
    "comment": "Лише додатні числа",
    "data": [
      [1, 1],
      [1, 1]
    ]
  },
  {
    "test_type": "Функціональний",
    "comment": "Лише від'ємні числа",
    "data": [
      [-1, -1],
      [-1, -1]
    ]
  },
  {
    "test_type": "Функціональний",
    "comment": "Різні числа",
    "data": [
      [1, -1],
      [1, -1]
    ]
  },
  {
    "test_type": "Функціональний",
    "comment": "Матриця 5x5",
    "data": [
      [1, 2, 3, 4, 5],
      [6, 7, 8, 9, 10],
      [11, 12, 13, 14, 15],
      [16, 17, 18, 19, 20],
      [21, 22, 23, 24, 25]
    ]
  },
  {
    "test_type": "Деструктивний",
    "comment": "Відсутність даних",
    "data": null
  },
  {
    "test_type": "Деструктивний",
    "comment": "Неправильний тип даних",
    "data": 8
  },
  {
    "test_type": "Деструктивний",
    "comment": "Неправильний тип даних",
    "data": [
      [1, 2, null],
      [4, "5", 6],
      [7, { "a": 8 }, 9]
    ]
  },
  {
    "test_type": "Деструктивний",
    "comment": "Не квадратна матриця",
    "data": [
      [1, 2, 3, 4],
      [5, 6, 7, 8],
      [9, 10, 11, 12]
    ]
  },
  {
    "test_type": "Деструктивний",
    "comment": "Пуста матриця",
    "data": []
  },
  {
    "test_type": "Деструктивний",
    "comment": "Нульова матриця",
    "data": [
      [0, 0, 0],
      [0, 0, 0],
      [0, 0, 0]
    ]
  }
]
